<?xml version="1.0" encoding="UTF-8" standalone="no"?>
<Patient_EHR>
  <Basic_Information>
    <DOB>908496000</DOB>
    <Date_Seen>1503705600</Date_Seen>
    <Gender>Female</Gender>
    <Marital_Status>Married</Marital_Status>
    <Consanguinity>No</Consanguinity>
  </Basic_Information>
  <Family_History>
    <Stroke>1</Stroke>
    <CAD>1</CAD>
    <Hyperlipidemia>1</Hyperlipidemia>
    <Hypertenison>1</Hypertenison>
    <Diabetes>1</Diabetes>
  </Family_History>
  <Social_History>
    <Current_Smoker>1</Current_Smoker>
    <Type_Of_Smoking>None</Type_Of_Smoking>
    <Hubble_Bubble_Per_Week>7</Hubble_Bubble_Per_Week>
    <Packs_Per_day>5</Packs_Per_day>
    <Number_of_Years>32</Number_of_Years>
    <Stopped_Since_Years>6</Stopped_Since_Years>
    <Alcohol>1</Alcohol>
  </Social_History>
  <Medications>
    <Vitamin_D>1</Vitamin_D>
    <B12>1</B12>
    <Fe>1</Fe>
    <Omega_3>1</Omega_3>
    <Panadol>1</Panadol>
    <Solpadeine>0</Solpadeine>
    <Antihistmaine>1</Antihistmaine>
    <PPI>1</PPI>
    <Mg>1</Mg>
    <OCP>1</OCP>
  </Medications>
  <Lab_Results>
    <Glycemia_>102</Glycemia_>
    <Creatinine>0.9</Creatinine>
    <Uric_acid>6.6</Uric_acid>
    <Cholesterol>281</Cholesterol>
    <HDL>100</HDL>
    <LDL>199</LDL>
    <Triglycerides>253</Triglycerides>
    <Calcium>10.8</Calcium>
    <Phophorous>5</Phophorous>
    <Magnesium>2.5</Magnesium>
    <Sodium>148</Sodium>
    <Potassium>5.5</Potassium>
    <Cholride>107</Cholride>
    <Total_Protetin>88</Total_Protetin>
    <Albumin>51</Albumin>
    <SGPT>43</SGPT>
    <CRP>34</CRP>
    <PTH>183.4</PTH>
    <Vit_D>37.96</Vit_D>
  </Lab_Results>
  <Vital_Signs>
    <Height_cm>182</Height_cm>
    <Weight_kg>88</Weight_kg>
    <BMI>29.7211</BMI>
  </Vital_Signs>
  <Pulse_Wave_Velocity>
    <PWV>7.5</PWV>
    <MGP>612.8</MGP>
    <SBP>130</SBP>
    <DBP>128</DBP>
    <PP>60</PP>
    <MBP>97</MBP>
    <HR>91</HR>
  </Pulse_Wave_Velocity>
</Patient_EHR>